LICENSE
MANIFEST.in
README.md
setup.py
oho/__init__.py
oho/__version__.py
oho/core.py
oho.egg-info/PKG-INFO
oho.egg-info/SOURCES.txt
oho.egg-info/dependency_links.txt
oho.egg-info/top_level.txt